esi_shakelib/__init__.py
esi_shakelib/ffsimmer.py
esi_shakelib/generic_site_amplitication.py
esi_shakelib/multigmpe.py
esi_shakelib/multiutils.py
esi_shakelib/sites.py
esi_shakelib/station.py
esi_shakelib/virtualipe.py
esi_shakelib/conversions/__init__.py
esi_shakelib/conversions/convert_imc.py
esi_shakelib/conversions/convert_imt.py
esi_shakelib/conversions/imc/__init__.py
esi_shakelib/conversions/imc/beyer_bommer_2006.py
esi_shakelib/conversions/imc/boore_kishida_2017.py
esi_shakelib/conversions/imc/data/nga-w2.lmR1M2_D00D50.4paper.RrupMin_0000.RrupMax_0400.Mmin_2.00.Mmax_9.00.csv
esi_shakelib/conversions/imc/data/nga-w2.lmR1M2_D100D00.4paper.RrupMin_0000.RrupMax_0400.Mmin_2.00.Mmax_9.00.csv
esi_shakelib/conversions/imc/data/nga-w2.lmR1M2_D100D50.4paper.RrupMin_0000.RrupMax_0400.Mmin_2.00.Mmax_9.00.csv
esi_shakelib/conversions/imc/data/nga-w2.lmR1M2_D50GM50.4paper.RrupMin_0000.RrupMax_0400.Mmin_2.00.Mmax_9.00.csv
esi_shakelib/conversions/imc/data/nga-w2.lmR1M2_D50GMAR.4paper.RrupMin_0000.RrupMax_0400.Mmin_2.00.Mmax_9.00.csv
esi_shakelib/conversions/imc/data/nga-w2.lmR1M2_LargerD100.4paper.RrupMin_0000.RrupMax_0400.Mmin_2.00.Mmax_9.00.csv
esi_shakelib/conversions/imc/data/nga-w2.lmR1M2_LargerD50.4paper.RrupMin_0000.RrupMax_0400.Mmin_2.00.Mmax_9.00.csv
esi_shakelib/conversions/imc/data/nga-w2.lmR1M2_LargerGM50.4paper.RrupMin_0000.RrupMax_0400.Mmin_2.00.Mmax_9.00.csv
esi_shakelib/conversions/imc/data/nga-w2.lmR1M2_LargerGMAR.4paper.RrupMin_0000.RrupMax_0400.Mmin_2.00.Mmax_9.00.csv
esi_shakelib/conversions/imt/__init__.py
esi_shakelib/conversions/imt/abrahamson_bhasin_2020.py
esi_shakelib/conversions/imt/bommer_alarcon_2006.py
esi_shakelib/conversions/imt/newmark_hall_1982.py
esi_shakelib/correlation/__init__.py
esi_shakelib/correlation/ccf_base.py
esi_shakelib/correlation/dummy.py
esi_shakelib/correlation/loth_baker_2013.py
esi_shakelib/directivity/__init__.py
esi_shakelib/directivity/bayless2013.py
esi_shakelib/directivity/rowshandel2013.py
esi_shakelib-1.1.13.dist-info/licenses/LICENSE.md
esi_shakelib-1.1.13.dist-info/METADATA
esi_shakelib-1.1.13.dist-info/WHEEL
esi_shakelib-1.1.13.dist-info/top_level.txt
esi_shakelib-1.1.13.dist-info/RECORD
