Metadata-Version: 2.4
Name: esi-shakelib
Version: 1.1.13
Summary: USGS Earthquake Impact Library for ShakeMap
Author-email: Bruce Worden <cbworden@contractor.usgs.gov>, Eric Thompson <emthompsone@usgs.gov>, Mike Hearne <mhearne@usgs.gov>
License: License
Requires-Python: >=3.9
License-File: LICENSE.md
Requires-Dist: esi-core>=1.2.3
Requires-Dist: esi-utils-colors>=1.0.3
Requires-Dist: esi-utils-rupture>=1.0.7
Requires-Dist: esi-utils-vectors>=1.0.2
Requires-Dist: importlib-resources
Requires-Dist: mapio>=0.8.8
Requires-Dist: cartopy>=0.22.0
Requires-Dist: gmpacket>=0.1.6
Requires-Dist: matplotlib>=3.8.0
Requires-Dist: numpy>=1.26
Requires-Dist: openquake.engine==3.23.2
Requires-Dist: numba
Requires-Dist: alpha-shapes>=1.0.0
Requires-Dist: pandas>=2.1.1
Requires-Dist: scipy>=1.11.2
Requires-Dist: shapely>=2.0.1
Requires-Dist: scikit-image>=0.21.0
Requires-Dist: usgs-strec>=2.2.8
Requires-Dist: dill
Provides-Extra: dev
Requires-Dist: build>=0.7.0; extra == "dev"
Requires-Dist: black>=21; extra == "dev"
Requires-Dist: flake8>=3.9; extra == "dev"
Requires-Dist: ipython>=7.26; extra == "dev"
Provides-Extra: test
Requires-Dist: pytest>=6.2; extra == "test"
Requires-Dist: pytest-cov>=2.12; extra == "test"
Provides-Extra: build
Requires-Dist: build; extra == "build"
Requires-Dist: packaging>=24.2; extra == "build"
Requires-Dist: twine; extra == "build"
Requires-Dist: check-wheel-contents; extra == "build"
Dynamic: license-file
